_dmcam.cp37-win32.pyd
dmcam.py
dmcam-1.82.7.data/data/Lib/site-packages/libdmcam.dll
dmcam-1.82.7.dist-info/METADATA
dmcam-1.82.7.dist-info/WHEEL
dmcam-1.82.7.dist-info/top_level.txt
dmcam-1.82.7.dist-info/RECORD
