Metadata-Version: 2.1
Name: dmcam
Version: 1.82.7
Summary: DM camera python extension
Home-page: https://github.com/smarttofsdk
Author: Zou yao
Author-email: zouyao@smarttof.com
License: UNKNOWN
Platform: UNKNOWN
Requires-Dist: numpy (>=1.12.0)
